opencivics/__init__.py
opencivics/api_extractor.py
opencivics/census.py
opencivics/mapping.py
opencivics/osm.py
opencivics-0.3.1.dist-info/METADATA
opencivics-0.3.1.dist-info/WHEEL
opencivics-0.3.1.dist-info/top_level.txt
opencivics-0.3.1.dist-info/RECORD
