Metadata-Version: 2.4
Name: opencivics
Version: 0.3.1
Summary: A comprehensive package for analyzing Australian geospatial data with PBF, OpenStreetMap Overpass API, and Google Maps API support
Author: Alexander Tashevski
License: MIT
Project-URL: Homepage, https://github.com/opencivics/opencivics-package
Project-URL: Documentation, https://opencivics.readthedocs.io
Project-URL: Repository, https://github.com/opencivics/opencivics-package
Project-URL: Issues, https://github.com/opencivics/opencivics-package/issues
Keywords: geospatial,australia,census,openstreetmap,mapping,civic
Classifier: Development Status :: 3 - Alpha
Classifier: Intended Audience :: Developers
Classifier: Intended Audience :: Science/Research
Classifier: Operating System :: OS Independent
Classifier: Programming Language :: Python :: 3
Classifier: Programming Language :: Python :: 3.8
Classifier: Programming Language :: Python :: 3.9
Classifier: Programming Language :: Python :: 3.10
Classifier: Programming Language :: Python :: 3.11
Classifier: Topic :: Scientific/Engineering :: GIS
Classifier: Topic :: Software Development :: Libraries :: Python Modules
Requires-Python: >=3.8
Requires-Dist: pandas>=1.3.0
Requires-Dist: geopandas>=0.10.0
Requires-Dist: shapely>=1.8.0
Requires-Dist: requests>=2.25.0
Requires-Dist: folium>=0.12.0
Requires-Dist: branca>=0.4.0
Requires-Dist: osmium>=3.2.0
Requires-Dist: numpy>=1.20.0
Requires-Dist: openpyxl>=3.0.0
Provides-Extra: dev
Requires-Dist: pytest>=6.0; extra == "dev"
Requires-Dist: pytest-cov>=2.12; extra == "dev"
Requires-Dist: black>=21.0; extra == "dev"
Requires-Dist: flake8>=3.9; extra == "dev"
Requires-Dist: mypy>=0.900; extra == "dev"
Requires-Dist: pre-commit>=2.15; extra == "dev"
Provides-Extra: docs
Requires-Dist: sphinx>=4.0; extra == "docs"
Requires-Dist: sphinx-rtd-theme>=1.0; extra == "docs"
Requires-Dist: myst-parser>=0.15; extra == "docs"
